auto_zkml/__init__.py
auto_zkml/model_reducer.py
auto_zkml/model_toolkit/__init__.py
auto_zkml/model_toolkit/custom_transformers/__init__.py
auto_zkml/model_toolkit/custom_transformers/customPCA.py
auto_zkml/model_toolkit/custom_transformers/customRFE.py
auto_zkml/model_toolkit/data_transformer.py
auto_zkml/model_toolkit/feature_models_space.py
auto_zkml/model_toolkit/metrics.py
auto_zkml/model_toolkit/model_evaluator.py
auto_zkml/model_toolkit/model_info.py
auto_zkml/model_toolkit/model_penalicer.py
auto_zkml/model_toolkit/model_trainer.py
auto_zkml/serializer/__init__py
auto_zkml/serializer/lgbm.py
auto_zkml/serializer/serialize.py
auto_zkml/serializer/xg.py
auto_zkml-0.1.0.dist-info/LICENSE
auto_zkml-0.1.0.dist-info/METADATA
auto_zkml-0.1.0.dist-info/WHEEL
auto_zkml-0.1.0.dist-info/RECORD
