Metadata-Version: 2.1
Name: auto-zkml
Version: 0.1.0
Summary: 
License: MIT
Author: Alejandro Martinez
Author-email: alejandro@gizatech.xyz
Requires-Python: >=3.11,<4.0
Classifier: License :: OSI Approved :: MIT License
Classifier: Programming Language :: Python :: 3
Classifier: Programming Language :: Python :: 3.11
Classifier: Programming Language :: Python :: 3.12
Requires-Dist: pandas (>=2.2.2,<3.0.0)
Requires-Dist: pydantic (>=2,<3)
Requires-Dist: rich (>=13,<14)
Requires-Dist: scikit-learn (>=1.4.2,<2.0.0)
Requires-Dist: scikit-optimize (>=0.10.1,<0.11.0)
